[
  {
    "vote": 1917,
    "timestamp": "1/24/2020",
    "category": "Best Picture"
  },
  {
    "vote": "Ford V Ferrari ",
    "timestamp": "1/24/2020",
    "category": "Best Picture"
  },
  {
    "vote": "Jojo Rabbit",
    "timestamp": "1/24/2020",
    "category": "Best Picture"
  },
  {
    "vote": 1917,
    "timestamp": "1/24/2020",
    "category": "Best Picture"
  },
  {
    "vote": "Parasite",
    "timestamp": "1/24/2020",
    "category": "Best Picture"
  },
  {
    "vote": "Ford V Ferrari ",
    "timestamp": "1/24/2020",
    "category": "Best Picture"
  },
  {
    "vote": "Pain and Glory",
    "timestamp": "1/24/2020",
    "category": "Best Actor"
  },
  {
    "vote": "Ford V Ferrari ",
    "timestamp": "1/24/2020",
    "category": "Best Picture"
  },
  {
    "vote": "The Irishman",
    "timestamp": "1/24/2020",
    "category": "Best Picture"
  },
  {
    "vote": "Marriage Story",
    "timestamp": "1/24/2020",
    "category": "Best Actor"
  },
  {
    "vote": "Joker",
    "timestamp": "1/24/2020",
    "category": "Best Actor"
  },
  {
    "vote": "The Two Popes",
    "timestamp": "1/24/2020",
    "category": "Best Actor"
  },
  {
    "vote": "The Two Popes",
    "timestamp": "1/24/2020",
    "category": "Best Actor"
  },
  {
    "vote": "The Two Popes",
    "timestamp": "1/24/2020",
    "category": "Best Actor"
  },
  {
    "vote": "Pain and Glory",
    "timestamp": "1/24/2020",
    "category": "Best Actor"
  }
]